setup.py
pyinsane.egg-info/PKG-INFO
pyinsane.egg-info/SOURCES.txt
pyinsane.egg-info/dependency_links.txt
pyinsane.egg-info/requires.txt
pyinsane.egg-info/top_level.txt
src/__init__.py
src/abstract.py
src/abstract_th.py
src/rawapi.py